{
  "Department": {
    "ID": "3",
    "Name": "Budget Betriebsbereiche",
    "Accountable": "Herr Kramer"
  },
  "ProductClass": {
    "ID": "5",
    "Name": "Gestaltung der Umwelt",
    "Accountable": "Dezernent II"
  },
  "ProductDomain": {
    "ID": "5",
    "Name": "Natur- und Landschaftspflege",
    "Responsible": "Frau Wichmann"
  },
  "ProductGroup": {
    "ID": "1",
    "Name": "Öffentliches Grün/Landschaftsbau",
    "Desc": "externes Produkt"
  },
  "Product": {
    "ID": "03",
    "Name": "Containerstellplätze",
    "LegalRequirement": "Freiwillige Aufgabe"
  },
  "Description": " Unterhaltung und Sauberhaltung der Wertstoffcontainerplätze",
  "Mission": " Vereinbarung zwischen der Entsorgungswirtschaft des Landkreises Harz AöR (enwi) und der Stadt Wernigerode",
  "Target": "Nutzer der Wertstoffcontainerplätze",
  "Objectives": " -Sauberhaltung der Stadt -Gewährung einer ordnungsgemäßen Entsorgung von Wertstoffen",
  "Services": " -Bereitstellung von Containerstandplätzen -Freischneiden von störendem Gehölzbewuchs -Bauliche Unterhaltung der Containerstandplätze -Sauberhaltung der Containerstandplätze -Übernahme der, Verkehrssicherungspflichteinschl. Durchführung des Winterdienstes,"
}