{
  "Balances": [
    {
      "Id": "100",
      "Class": "one-off",
      "Desc": "Anschaffungen 150 €  bis 1.000 € netto",
      "Budgets": {
        "2020": -3259.92,
        "2021": 0,
        "2022": 0,
        "2023": 0,
        "2024": 0,
        "2025": 0
      },
      "Accounts": [
        {
          "Id": "40",
          "Desc": " -Auszahlungen für den Erwerb von beweglichen Vermögensgegenständen",
          "Budgets": {
            "2020": 3259.92,
            "2021": 0,
            "2022": 0,
            "2023": 0,
            "2024": 0,
            "2025": 0
          },
          "Subs": [
            {
              "Id": "",
              "Desc": "",
              "Budgets": null,
              "Units": [
                {
                  "Id": "5.4.1.01/0100.7832000",
                  "Desc": "Ausz. f.d. Erw. v. beweg. Vermögensgegenständen v. \u003e 150  bis 1000 € o. UStr.",
                  "AboveValueLimit": null,
                  "Budgets": {
                    "2020": 3259.92,
                    "2021": 0,
                    "2022": 0,
                    "2023": 0,
                    "2024": 0,
                    "2025": 0
                  }
                }
              ]
            }
          ]
        }
      ]
    },
    {
      "Id": "200",
      "Class": "one-off",
      "Desc": "Betriebs-und Geschäftsausstattungen",
      "Budgets": {
        "2020": 0,
        "2021": 0,
        "2022": 0,
        "2023": 0,
        "2024": 0,
        "2025": 0
      },
      "Accounts": null
    },
    {
      "Id": "300",
      "Class": "one-off",
      "Desc": "Betriebsvorrichtungen",
      "Budgets": {
        "2020": -3419.68,
        "2021": -4000,
        "2022": 0,
        "2023": 0,
        "2024": 0,
        "2025": 0
      },
      "Accounts": [
        {
          "Id": "40",
          "Desc": " -Auszahlungen für den Erwerb von beweglichen Vermögensgegenständen",
          "Budgets": {
            "2020": 3419.68,
            "2021": 4000,
            "2022": 0,
            "2023": 0,
            "2024": 0,
            "2025": 0
          },
          "Subs": [
            {
              "Id": "",
              "Desc": "",
              "Budgets": null,
              "Units": [
                {
                  "Id": "5.4.1.01/0300.7831000",
                  "Desc": "Auszahl. f.d. Erw. von bewegl. Vermögengeg.st. von mehr als 1000 Euro ohne UStr.",
                  "AboveValueLimit": null,
                  "Budgets": {
                    "2020": 3419.68,
                    "2021": 4000,
                    "2022": 0,
                    "2023": 0,
                    "2024": 0,
                    "2025": 0
                  }
                }
              ]
            }
          ]
        }
      ]
    },
    {
      "Id": "3001",
      "Class": "one-off",
      "Desc": "Schmutz-und Regenwasseranschlüsse für städtische Grundstücke",
      "Budgets": {
        "2020": 0,
        "2021": 0,
        "2022": 0,
        "2023": 0,
        "2024": 0,
        "2025": 0
      },
      "Accounts": null
    },
    {
      "Id": "3002",
      "Class": "one-off",
      "Desc": "Geh-und Radwege",
      "Budgets": {
        "2020": -26448.64,
        "2021": -100000,
        "2022": -100000,
        "2023": -100000,
        "2024": -100000,
        "2025": -100000
      },
      "Accounts": [
        {
          "Id": "50",
          "Desc": " -Auszahlungen für Baumaßnahmen",
          "Budgets": {
            "2020": 26448.64,
            "2021": 100000,
            "2022": 100000,
            "2023": 100000,
            "2024": 100000,
            "2025": 100000
          },
          "Subs": [
            {
              "Id": "",
              "Desc": "",
              "Budgets": null,
              "Units": [
                {
                  "Id": "5.4.1.01/3002.7852000",
                  "Desc": "Auszahlungen für Tiefbaumaßnahmen",
                  "AboveValueLimit": null,
                  "Budgets": {
                    "2020": 26448.64,
                    "2021": 100000,
                    "2022": 100000,
                    "2023": 100000,
                    "2024": 100000,
                    "2025": 100000
                  }
                }
              ]
            }
          ]
        }
      ]
    },
    {
      "Id": "3203",
      "Class": "one-off",
      "Desc": "Brücke Steinerne Renne BW 567",
      "Budgets": {
        "2020": 0,
        "2021": 0,
        "2022": 0,
        "2023": 0,
        "2024": 0,
        "2025": 0
      },
      "Accounts": null
    },
    {
      "Id": "3204",
      "Class": "one-off",
      "Desc": "Brücke Kruskastraße",
      "Budgets": {
        "2020": -18635.21,
        "2021": -50000,
        "2022": -90000,
        "2023": 0,
        "2024": 0,
        "2025": 0
      },
      "Accounts": [
        {
          "Id": "50",
          "Desc": " -Auszahlungen für Baumaßnahmen",
          "Budgets": {
            "2020": 18635.21,
            "2021": 50000,
            "2022": 90000,
            "2023": 0,
            "2024": 0,
            "2025": 0
          },
          "Subs": [
            {
              "Id": "",
              "Desc": "",
              "Budgets": null,
              "Units": [
                {
                  "Id": "5.4.1.01/3204.7852000",
                  "Desc": "Auszahlungen für Tiefbaumaßnahmen",
                  "AboveValueLimit": null,
                  "Budgets": {
                    "2020": 18635.21,
                    "2021": 50000,
                    "2022": 90000,
                    "2023": 0,
                    "2024": 0,
                    "2025": 0
                  }
                }
              ]
            }
          ]
        }
      ]
    },
    {
      "Id": "3205",
      "Class": "one-off",
      "Desc": "Brücke Hasenwinkel, Bw 574 Planung / Bau gekürzt",
      "Budgets": {
        "2020": 0,
        "2021": 0,
        "2022": -80000,
        "2023": -450000,
        "2024": 0,
        "2025": 0
      },
      "Accounts": [
        {
          "Id": "50",
          "Desc": " -Auszahlungen für Baumaßnahmen",
          "Budgets": {
            "2020": 0,
            "2021": 0,
            "2022": 80000,
            "2023": 450000,
            "2024": 0,
            "2025": 0
          },
          "Subs": [
            {
              "Id": "",
              "Desc": "",
              "Budgets": null,
              "Units": [
                {
                  "Id": "5.4.1.01/3205.7852000",
                  "Desc": "Auszahlungen für Tiefbaumaßnahmen",
                  "AboveValueLimit": null,
                  "Budgets": {
                    "2020": 0,
                    "2021": 0,
                    "2022": 80000,
                    "2023": 450000,
                    "2024": 0,
                    "2025": 0
                  }
                }
              ]
            }
          ]
        }
      ]
    },
    {
      "Id": "3303",
      "Class": "one-off",
      "Desc": "Straße Am Eichberg (Teilabschnitt)",
      "Budgets": {
        "2020": 0,
        "2021": 0,
        "2022": 0,
        "2023": 0,
        "2024": 0,
        "2025": 0
      },
      "Accounts": null
    },
    {
      "Id": "3304",
      "Class": "one-off",
      "Desc": "Nöschenröder Straße B 244",
      "Budgets": {
        "2020": 0,
        "2021": 0,
        "2022": 0,
        "2023": 0,
        "2024": 0,
        "2025": 0
      },
      "Accounts": null
    },
    {
      "Id": "3305",
      "Class": "one-off",
      "Desc": "Kreisverkehr B6/L82",
      "Budgets": {
        "2020": 0,
        "2021": 0,
        "2022": 0,
        "2023": 0,
        "2024": 0,
        "2025": 0
      },
      "Accounts": null
    },
    {
      "Id": "3306",
      "Class": "one-off",
      "Desc": "Friedrichstraße L100",
      "Budgets": {
        "2020": 0,
        "2021": -900000,
        "2022": -600000,
        "2023": -300000,
        "2024": 0,
        "2025": 0
      },
      "Accounts": [
        {
          "Id": "50",
          "Desc": " -Auszahlungen für Baumaßnahmen",
          "Budgets": {
            "2020": 0,
            "2021": 900000,
            "2022": 600000,
            "2023": 300000,
            "2024": 0,
            "2025": 0
          },
          "Subs": [
            {
              "Id": "",
              "Desc": "",
              "Budgets": null,
              "Units": [
                {
                  "Id": "5.4.1.01/3306.7852000",
                  "Desc": "Auszahlungen für Tiefbaumaßnahmen",
                  "AboveValueLimit": null,
                  "Budgets": {
                    "2020": 0,
                    "2021": 900000,
                    "2022": 600000,
                    "2023": 300000,
                    "2024": 0,
                    "2025": 0
                  }
                }
              ]
            }
          ]
        }
      ]
    },
    {
      "Id": "3309",
      "Class": "one-off",
      "Desc": "Straße An der Malzmühle",
      "Budgets": {
        "2020": 0,
        "2021": 0,
        "2022": 0,
        "2023": 0,
        "2024": 0,
        "2025": 0
      },
      "Accounts": null
    },
    {
      "Id": "3319",
      "Class": "one-off",
      "Desc": "Kirchstr.",
      "Budgets": {
        "2020": 0,
        "2021": 0,
        "2022": 0,
        "2023": 0,
        "2024": 0,
        "2025": 0
      },
      "Accounts": null
    },
    {
      "Id": "3320",
      "Class": "one-off",
      "Desc": "Stützmauern",
      "Budgets": {
        "2020": -109125.79,
        "2021": -80000,
        "2022": -80000,
        "2023": 0,
        "2024": -80000,
        "2025": 0
      },
      "Accounts": [
        {
          "Id": "50",
          "Desc": " -Auszahlungen für Baumaßnahmen",
          "Budgets": {
            "2020": 109125.79,
            "2021": 80000,
            "2022": 80000,
            "2023": 0,
            "2024": 80000,
            "2025": 0
          },
          "Subs": [
            {
              "Id": "",
              "Desc": "",
              "Budgets": null,
              "Units": [
                {
                  "Id": "5.4.1.01/3320.7851000",
                  "Desc": "Auszahlungen für Hochbaumaßnahmen",
                  "AboveValueLimit": null,
                  "Budgets": {
                    "2020": 44385.84,
                    "2021": 0,
                    "2022": 0,
                    "2023": 0,
                    "2024": 0,
                    "2025": 0
                  }
                },
                {
                  "Id": "5.4.1.01/3320.7852000",
                  "Desc": "Auszahlungen für Tiefbaumaßnahmen",
                  "AboveValueLimit": null,
                  "Budgets": {
                    "2020": 64739.95,
                    "2021": 80000,
                    "2022": 80000,
                    "2023": 0,
                    "2024": 80000,
                    "2025": 0
                  }
                }
              ]
            }
          ]
        }
      ]
    },
    {
      "Id": "3323",
      "Class": "one-off",
      "Desc": "Straße Am Schloß",
      "Budgets": {
        "2020": 0,
        "2021": -50000,
        "2022": -100000,
        "2023": -50000,
        "2024": -250000,
        "2025": 0
      },
      "Accounts": [
        {
          "Id": "50",
          "Desc": " -Auszahlungen für Baumaßnahmen",
          "Budgets": {
            "2020": 0,
            "2021": 50000,
            "2022": 100000,
            "2023": 50000,
            "2024": 250000,
            "2025": 0
          },
          "Subs": [
            {
              "Id": "",
              "Desc": "",
              "Budgets": null,
              "Units": [
                {
                  "Id": "5.4.1.01/3323.7852000",
                  "Desc": "Auszahlungen für Tiefbaumaßnahmen",
                  "AboveValueLimit": null,
                  "Budgets": {
                    "2020": 0,
                    "2021": 50000,
                    "2022": 100000,
                    "2023": 50000,
                    "2024": 250000,
                    "2025": 0
                  }
                }
              ]
            }
          ]
        }
      ]
    },
    {
      "Id": "3327",
      "Class": "one-off",
      "Desc": "Feldstr. Lückenschluss",
      "Budgets": {
        "2020": 0,
        "2021": 0,
        "2022": 0,
        "2023": 0,
        "2024": 0,
        "2025": 0
      },
      "Accounts": null
    },
    {
      "Id": "3328",
      "Class": "one-off",
      "Desc": "Umgehungsstr. Nord Silstedt",
      "Budgets": {
        "2020": 0,
        "2021": 0,
        "2022": 0,
        "2023": 0,
        "2024": 0,
        "2025": 0
      },
      "Accounts": null
    },
    {
      "Id": "3338",
      "Class": "one-off",
      "Desc": "Insel 2. bis 3. BA",
      "Budgets": {
        "2020": -141759.8,
        "2021": -50000,
        "2022": 0,
        "2023": -150000,
        "2024": 0,
        "2025": 0
      },
      "Accounts": [
        {
          "Id": "50",
          "Desc": " -Auszahlungen für Baumaßnahmen",
          "Budgets": {
            "2020": 141759.8,
            "2021": 50000,
            "2022": 0,
            "2023": 150000,
            "2024": 0,
            "2025": 0
          },
          "Subs": [
            {
              "Id": "",
              "Desc": "",
              "Budgets": null,
              "Units": [
                {
                  "Id": "5.4.1.01/3338.7852000",
                  "Desc": "Auszahlungen für Tiefbaumaßnahmen",
                  "AboveValueLimit": null,
                  "Budgets": {
                    "2020": 141759.8,
                    "2021": 50000,
                    "2022": 0,
                    "2023": 150000,
                    "2024": 0,
                    "2025": 0
                  }
                }
              ]
            }
          ]
        }
      ]
    },
    {
      "Id": "3339",
      "Class": "one-off",
      "Desc": "Schierke Brockenstraße Stich Feuerwehr",
      "Budgets": {
        "2020": -168436.94,
        "2021": 0,
        "2022": 0,
        "2023": 0,
        "2024": 0,
        "2025": 0
      },
      "Accounts": [
        {
          "Id": "50",
          "Desc": " -Auszahlungen für Baumaßnahmen",
          "Budgets": {
            "2020": 168436.94,
            "2021": 0,
            "2022": 0,
            "2023": 0,
            "2024": 0,
            "2025": 0
          },
          "Subs": [
            {
              "Id": "",
              "Desc": "",
              "Budgets": null,
              "Units": [
                {
                  "Id": "5.4.1.01/3339.7852000",
                  "Desc": "Auszahlungen für Tiefbaumaßnahmen",
                  "AboveValueLimit": null,
                  "Budgets": {
                    "2020": 168436.94,
                    "2021": 0,
                    "2022": 0,
                    "2023": 0,
                    "2024": 0,
                    "2025": 0
                  }
                }
              ]
            }
          ]
        }
      ]
    },
    {
      "Id": "3340",
      "Class": "one-off",
      "Desc": "Straße Ochsenteich",
      "Budgets": {
        "2020": 0,
        "2021": 0,
        "2022": 0,
        "2023": 0,
        "2024": 0,
        "2025": 0
      },
      "Accounts": null
    },
    {
      "Id": "3341",
      "Class": "one-off",
      "Desc": "Louis-Braille-Straße",
      "Budgets": {
        "2020": -14100,
        "2021": -500000,
        "2022": -600000,
        "2023": 0,
        "2024": 0,
        "2025": 0
      },
      "Accounts": [
        {
          "Id": "50",
          "Desc": " -Auszahlungen für Baumaßnahmen",
          "Budgets": {
            "2020": 14100,
            "2021": 500000,
            "2022": 600000,
            "2023": 0,
            "2024": 0,
            "2025": 0
          },
          "Subs": [
            {
              "Id": "",
              "Desc": "",
              "Budgets": null,
              "Units": [
                {
                  "Id": "5.4.1.01/3341.7852000",
                  "Desc": "Auszahlungen für Tiefbaumaßnahmen",
                  "AboveValueLimit": null,
                  "Budgets": {
                    "2020": 14100,
                    "2021": 500000,
                    "2022": 600000,
                    "2023": 0,
                    "2024": 0,
                    "2025": 0
                  }
                }
              ]
            }
          ]
        }
      ]
    },
    {
      "Id": "3342",
      "Class": "one-off",
      "Desc": "Minsleben, Gartenbreite - Anteil zu ländl. Wegebau",
      "Budgets": {
        "2020": -12922.82,
        "2021": 0,
        "2022": 0,
        "2023": 0,
        "2024": 0,
        "2025": 0
      },
      "Accounts": [
        {
          "Id": "50",
          "Desc": " -Auszahlungen für Baumaßnahmen",
          "Budgets": {
            "2020": 12922.82,
            "2021": 0,
            "2022": 0,
            "2023": 0,
            "2024": 0,
            "2025": 0
          },
          "Subs": [
            {
              "Id": "",
              "Desc": "",
              "Budgets": null,
              "Units": [
                {
                  "Id": "5.4.1.01/3342.7852000",
                  "Desc": "Auszahlungen für Tiefbaumaßnahmen",
                  "AboveValueLimit": null,
                  "Budgets": {
                    "2020": 12922.82,
                    "2021": 0,
                    "2022": 0,
                    "2023": 0,
                    "2024": 0,
                    "2025": 0
                  }
                }
              ]
            }
          ]
        }
      ]
    },
    {
      "Id": "3345",
      "Class": "one-off",
      "Desc": "Schierke Geländeprofil Plaza PH/Loipe Barenberg",
      "Budgets": {
        "2020": 0,
        "2021": -15000,
        "2022": -20000,
        "2023": 0,
        "2024": 0,
        "2025": 0
      },
      "Accounts": [
        {
          "Id": "50",
          "Desc": " -Auszahlungen für Baumaßnahmen",
          "Budgets": {
            "2020": 0,
            "2021": 15000,
            "2022": 20000,
            "2023": 0,
            "2024": 0,
            "2025": 0
          },
          "Subs": [
            {
              "Id": "",
              "Desc": "",
              "Budgets": null,
              "Units": [
                {
                  "Id": "5.4.1.01/3345.7852000",
                  "Desc": "Auszahlungen für Tiefbaumaßnahmen",
                  "AboveValueLimit": null,
                  "Budgets": {
                    "2020": 0,
                    "2021": 15000,
                    "2022": 20000,
                    "2023": 0,
                    "2024": 0,
                    "2025": 0
                  }
                }
              ]
            }
          ]
        }
      ]
    },
    {
      "Id": "3347",
      "Class": "one-off",
      "Desc": "Walther-Rathenau-Straße",
      "Budgets": {
        "2020": 0,
        "2021": 0,
        "2022": 0,
        "2023": 0,
        "2024": 0,
        "2025": 0
      },
      "Accounts": null
    },
    {
      "Id": "3348",
      "Class": "one-off",
      "Desc": "Am Großer Bleek (2007 MN 63)",
      "Budgets": {
        "2020": 0,
        "2021": 0,
        "2022": 0,
        "2023": 0,
        "2024": 0,
        "2025": 0
      },
      "Accounts": null
    },
    {
      "Id": "3349",
      "Class": "one-off",
      "Desc": "Minslebener Straße (Restbreiten)",
      "Budgets": {
        "2020": 0,
        "2021": 0,
        "2022": 0,
        "2023": 0,
        "2024": -300000,
        "2025": 0
      },
      "Accounts": [
        {
          "Id": "50",
          "Desc": " -Auszahlungen für Baumaßnahmen",
          "Budgets": {
            "2020": 0,
            "2021": 0,
            "2022": 0,
            "2023": 0,
            "2024": 300000,
            "2025": 0
          },
          "Subs": [
            {
              "Id": "",
              "Desc": "",
              "Budgets": null,
              "Units": [
                {
                  "Id": "5.4.1.01/3349.7852000",
                  "Desc": "Auszahlungen für Tiefbaumaßnahmen",
                  "AboveValueLimit": null,
                  "Budgets": {
                    "2020": 0,
                    "2021": 0,
                    "2022": 0,
                    "2023": 0,
                    "2024": 300000,
                    "2025": 0
                  }
                }
              ]
            }
          ]
        }
      ]
    },
    {
      "Id": "3352",
      "Class": "one-off",
      "Desc": "",
      "Budgets": {
        "2020": 0,
        "2021": 0,
        "2022": 0,
        "2023": 0,
        "2024": 0,
        "2025": 0
      },
      "Accounts": null
    },
    {
      "Id": "3353",
      "Class": "one-off",
      "Desc": "Schreiberstraße (Restbreiten)",
      "Budgets": {
        "2020": 0,
        "2021": 0,
        "2022": 0,
        "2023": -200000,
        "2024": 0,
        "2025": -200000
      },
      "Accounts": [
        {
          "Id": "50",
          "Desc": " -Auszahlungen für Baumaßnahmen",
          "Budgets": {
            "2020": 0,
            "2021": 0,
            "2022": 0,
            "2023": 200000,
            "2024": 0,
            "2025": 200000
          },
          "Subs": [
            {
              "Id": "",
              "Desc": "",
              "Budgets": null,
              "Units": [
                {
                  "Id": "5.4.1.01/3353.7852000",
                  "Desc": "Auszahlungen für Tiefbaumaßnahmen",
                  "AboveValueLimit": null,
                  "Budgets": {
                    "2020": 0,
                    "2021": 0,
                    "2022": 0,
                    "2023": 200000,
                    "2024": 0,
                    "2025": 200000
                  }
                }
              ]
            }
          ]
        }
      ]
    },
    {
      "Id": "3900",
      "Class": "one-off",
      "Desc": "Strab für Straßen Wernigerode",
      "Budgets": {
        "2020": 0,
        "2021": 0,
        "2022": 0,
        "2023": 0,
        "2024": 0,
        "2025": 0
      },
      "Accounts": null
    },
    {
      "Id": "3901",
      "Class": "one-off",
      "Desc": "wiederkehrende Strab Straßen Benzingerode",
      "Budgets": {
        "2020": 0,
        "2021": 0,
        "2022": 0,
        "2023": 0,
        "2024": 0,
        "2025": 0
      },
      "Accounts": null
    },
    {
      "Id": "3902",
      "Class": "one-off",
      "Desc": "wiederkehrende Strab Straßen Silstedt",
      "Budgets": {
        "2020": 0,
        "2021": 0,
        "2022": 0,
        "2023": 0,
        "2024": 0,
        "2025": 0
      },
      "Accounts": null
    },
    {
      "Id": "3903",
      "Class": "one-off",
      "Desc": "wiederkehrende Strab Straßen Schierke",
      "Budgets": {
        "2020": 0,
        "2021": 0,
        "2022": 0,
        "2023": 0,
        "2024": 0,
        "2025": 0
      },
      "Accounts": null
    },
    {
      "Id": "5002",
      "Class": "one-off",
      "Desc": "Parkscheinautomaten",
      "Budgets": {
        "2020": -62758.36,
        "2021": 0,
        "2022": 0,
        "2023": 0,
        "2024": 0,
        "2025": 0
      },
      "Accounts": [
        {
          "Id": "50",
          "Desc": " -Auszahlungen für Baumaßnahmen",
          "Budgets": {
            "2020": 62758.36,
            "2021": 0,
            "2022": 0,
            "2023": 0,
            "2024": 0,
            "2025": 0
          },
          "Subs": [
            {
              "Id": "",
              "Desc": "",
              "Budgets": null,
              "Units": [
                {
                  "Id": "5.4.1.01/5002.7853000",
                  "Desc": "Auszahlungen für sonstige Baumaßnahmen",
                  "AboveValueLimit": null,
                  "Budgets": {
                    "2020": 62758.36,
                    "2021": 0,
                    "2022": 0,
                    "2023": 0,
                    "2024": 0,
                    "2025": 0
                  }
                }
              ]
            }
          ]
        }
      ]
    },
    {
      "Id": "6666",
      "Class": "one-off",
      "Desc": "Bauliche Anlagen des Infrastrukturvermögens",
      "Budgets": {
        "2020": -1146.84,
        "2021": -25000,
        "2022": -30500,
        "2023": -9000,
        "2024": -9000,
        "2025": -9000
      },
      "Accounts": [
        {
          "Id": "50",
          "Desc": " -Auszahlungen für Baumaßnahmen",
          "Budgets": {
            "2020": 1146.84,
            "2021": 25000,
            "2022": 30500,
            "2023": 9000,
            "2024": 9000,
            "2025": 9000
          },
          "Subs": [
            {
              "Id": "",
              "Desc": "",
              "Budgets": null,
              "Units": [
                {
                  "Id": "5.4.1.01/6666.7853000",
                  "Desc": "Auszahlungen für sonstige Baumaßnahmen",
                  "AboveValueLimit": null,
                  "Budgets": {
                    "2020": 1146.84,
                    "2021": 25000,
                    "2022": 30500,
                    "2023": 9000,
                    "2024": 9000,
                    "2025": 9000
                  }
                }
              ]
            }
          ]
        }
      ]
    },
    {
      "Id": "7005",
      "Class": "one-off",
      "Desc": "Zuschuss Aufwendungsersatz Regenwasser WAHB",
      "Budgets": {
        "2020": -398856.53,
        "2021": -400000,
        "2022": 0,
        "2023": 0,
        "2024": 0,
        "2025": 0
      },
      "Accounts": [
        {
          "Id": "40",
          "Desc": " -Auszahlungen für den Erwerb von beweglichen Vermögensgegenständen",
          "Budgets": {
            "2020": 398856.53,
            "2021": 400000,
            "2022": 0,
            "2023": 0,
            "2024": 0,
            "2025": 0
          },
          "Subs": [
            {
              "Id": "",
              "Desc": "",
              "Budgets": null,
              "Units": [
                {
                  "Id": "5.4.1.01/7005.7834000",
                  "Desc": "Auszahlung für den Erwerb immaterieller Vermögensgegenstände",
                  "AboveValueLimit": null,
                  "Budgets": {
                    "2020": 398856.53,
                    "2021": 400000,
                    "2022": 0,
                    "2023": 0,
                    "2024": 0,
                    "2025": 0
                  }
                }
              ]
            }
          ]
        }
      ]
    },
    {
      "Id": "8888",
      "Class": "one-off",
      "Desc": "mittelfristige Maßnahmen",
      "Budgets": {
        "2020": 0,
        "2021": 0,
        "2022": 0,
        "2023": -200000,
        "2024": 0,
        "2025": 0
      },
      "Accounts": [
        {
          "Id": "50",
          "Desc": " -Auszahlungen für Baumaßnahmen",
          "Budgets": {
            "2020": 0,
            "2021": 0,
            "2022": 0,
            "2023": 200000,
            "2024": 0,
            "2025": 0
          },
          "Subs": [
            {
              "Id": "",
              "Desc": "",
              "Budgets": null,
              "Units": [
                {
                  "Id": "5.4.1.01/8888.7852000",
                  "Desc": "Auszahlungen für Tiefbaumaßnahmen",
                  "AboveValueLimit": null,
                  "Budgets": {
                    "2020": 0,
                    "2021": 0,
                    "2022": 0,
                    "2023": 200000,
                    "2024": 0,
                    "2025": 0
                  }
                }
              ]
            }
          ]
        }
      ]
    }
  ]
}