{
  "Department": {
    "ID": "4",
    "Name": "Budget B端rgerservice",
    "Accountable": "Herr Dorff"
  },
  "ProductClass": {
    "ID": "2",
    "Name": "Schule und Kultur",
    "Accountable": "Dezernent I"
  },
  "ProductDomain": {
    "ID": "4",
    "Name": "Weitere schulische Aufgaben",
    "Responsible": "Frau Lisowski"
  },
  "ProductGroup": {
    "ID": "3",
    "Name": "Sonstige schulische Aufgaben",
    "Desc": "externes Produkt"
  },
  "Product": {
    "ID": "01",
    "Name": "Sonstige schulische Aufgaben",
    "LegalRequirement": "Pflichtaufgabe"
  },
  "Description": " Sonstige schulische Aufgaben",
  "Mission": " Bundes-, Landes- und Ortsrecht",
  "Target": "Sch端lerinnen und Sch端ler, Eltern, Schulleitungen, kommunale MitarbeiterInnen, Institutionen",
  "Objectives": " Reibungsloser Ablauf des Schulbetriebes,,,,",
  "Services": " -Sch端ler- und Elternvertretungsangelegenheiten -Sonstige Verwaltungsleistungen -Mitwirkung bei der Schulentwicklungsplanung des Landkreises,"
}